.gitignore
AUTHORS.rst
COPYING.txt
README.rst
TODO.org
TODO.org_archive
setup.py
doc/Makefile
doc/api.rst
doc/conf.py
doc/index.rst
examples/dumpdb_demo.py
examples/map_demo.py
examples/plot_am_tone.py
examples/plot_period_histogram.py
examples/plot_spikes.py
examples/thorns_demo.ipynb
tests/test_bisection.py
tests/test_dumpdb.py
tests/test_map.py
tests/test_map_nested.py
tests/test_spikes.py
tests/test_stats.py
tests/test_waves.py
thorns/__init__.py
thorns/io.py
thorns/nrn.py
thorns/plotting.py
thorns/spikes.py
thorns/stats.py
thorns/waves.py
thorns/waves_old.py
thorns.egg-info/PKG-INFO
thorns.egg-info/SOURCES.txt
thorns.egg-info/dependency_links.txt
thorns.egg-info/requires.txt
thorns.egg-info/top_level.txt
thorns/datasets/__init__.py
thorns/datasets/anf_zilany2014.pkl
thorns/datasets/generate_anf_zilany2014.py
thorns/util/__init__.py
thorns/util/bisection.py
thorns/util/dumpdb.py
thorns/util/maps.py
thorns/util/run_func.py