Metadata-Version: 1.1
Name: thorns
Version: 1
Summary: Spike analysis software
Home-page: https://github.com/mrkrd/thorns
Author: Marek Rudnicki
Author-email: marek.rudnicki@tum.de
License: GPLv3+
Download-URL: https://github.com/mrkrd/thorns/tarball/master
Platform: Linux
Platform: Windows
Platform: FreeBSD
Classifier: Development Status :: 4 - Beta
Classifier: Environment :: Console
Classifier: Intended Audience :: End Users/Desktop
Classifier: Intended Audience :: Science/Research
Classifier: License :: OSI Approved :: GNU General Public License v3 or later (GPLv3+)
Classifier: Operating System :: POSIX
Classifier: Operating System :: Microsoft :: Windows
Classifier: Operating System :: MacOS :: MacOS X
Classifier: Programming Language :: Python
Classifier: Programming Language :: Python :: 2.7
